dash_lazylog
