Metadata-Version: 1.1
Name: dash-lazylog
Version: 0.0.2
Summary: Dash wrapper for react-lazylog: https://www.npmjs.com/package/react-lazylog
Home-page: UNKNOWN
Author: Jacob Roberts <jacoberts@gmail.com>
Author-email: UNKNOWN
License: MIT
Platform: UNKNOWN
Classifier: Framework :: Dash
